tapioca_rocketchat/__init__.py
tapioca_rocketchat/adapter.py
tapioca_rocketchat/auth.py
tapioca_rocketchat/resources.py
tapioca_rocketchat-0.1.dist-info/DESCRIPTION.rst
tapioca_rocketchat-0.1.dist-info/METADATA
tapioca_rocketchat-0.1.dist-info/RECORD
tapioca_rocketchat-0.1.dist-info/WHEEL
tapioca_rocketchat-0.1.dist-info/metadata.json
tapioca_rocketchat-0.1.dist-info/top_level.txt
