Metadata-Version: 2.0
Name: tapioca-rocketchat
Version: 0.1
Summary: Rocket.Chat API wrapper using tapioca
Home-page: https://github.com/eliostvs/tapioca-rocketchat
Author: Elio E. Duarte
Author-email: elio.esteves.duarte@gmail.com
License: MIT
Keywords: rocketchat
Platform: UNKNOWN
Classifier: Development Status :: 5 - Production/Stable
Classifier: Intended Audience :: Developers
Classifier: License :: OSI Approved :: MIT License
Classifier: Natural Language :: English
Classifier: Programming Language :: Python :: 2
Classifier: Programming Language :: Python :: 2.7
Classifier: Programming Language :: Python :: 3
Classifier: Programming Language :: Python :: 3.1
Classifier: Programming Language :: Python :: 3.2
Classifier: Programming Language :: Python :: 3.3
Classifier: Programming Language :: Python :: 3.4
Classifier: Programming Language :: Python :: 3.5
Requires-Dist: tapioca-wrapper (==1.2.3)
